biceps/Analysis.py
biceps/J_coupling.py
biceps/KarplusRelation.py
biceps/PosteriorSampler.py
biceps/Restraint.py
biceps/__init__.py
biceps/convergence.py
biceps/decorators.py
biceps/toolbox.py
biceps-2.0.0.dist-info/AUTHORS
biceps-2.0.0.dist-info/COPYING
biceps-2.0.0.dist-info/METADATA
biceps-2.0.0.dist-info/WHEEL
biceps-2.0.0.dist-info/top_level.txt
biceps-2.0.0.dist-info/RECORD
