Metadata-Version: 2.1
Name: biceps
Version: 2.0.0
Summary: BICePs
Home-page: https://biceps.readthedocs.io/en/latest/index.html
Author: Robert M. Raddi, Yunhui Ge, Vincent A. Voelz
Author-email: rraddi@temple.edu, yunhui.ge@gmail.com, vvoelz@gmail.com
License: MIT
Project-URL: Github, https://github.com/vvoelz/biceps
Project-URL: Documentation, https://biceps.readthedocs.io/en/latest/index.html
Classifier: Programming Language :: Python :: 3
Classifier: License :: OSI Approved :: MIT License
Classifier: Operating System :: MacOS
Classifier: Operating System :: Unix
Classifier: Intended Audience :: Developers
Classifier: Intended Audience :: Science/Research
Classifier: Topic :: Scientific/Engineering :: Chemistry
Classifier: Topic :: Scientific/Engineering :: Bio-Informatics
Requires-Python: >=3.7
License-File: COPYING
License-File: AUTHORS
Requires-Dist: cython (>=0.28)
Requires-Dist: numpy (>=1.7.0)
Requires-Dist: natsort
Requires-Dist: matplotlib
Requires-Dist: scikit-learn
Requires-Dist: pandas
Requires-Dist: scipy
Requires-Dist: tqdm
Requires-Dist: pymbar (>=4.0.1)
Requires-Dist: mdtraj
